[{"coref_chain": "ACT17720047052937775", "doc_id": "36_10ecbplus", "is_continuous": true, "is_singleton": true, "mention_id": "36_10ecbplus_ACT17720047052937775_3_24", "mention_type": "ACT", "mention_full_type": "ACTION_OCCURRENCE", "score": -1.0, "sent_id": 2, "tokens_number": [24], "tokens_str": "rape", "topic_id": "36ecbplus", "coref_type": "CROSS_DOC_COREF", "decription": "t36_rape_14_yr_old"}, {"coref_chain": "ACT17720769677783913", "doc_id": "36_10ecbplus", "is_continuous": true, "is_singleton": false, "mention_id": "36_10ecbplus_ACT17720769677783913_1_4", "mention_type": "ACT", "mention_full_type": "ACTION_OCCURRENCE", "score": -1.0, "sent_id": 0, "tokens_number": [4], "tokens_str": "charged", "topic_id": "36ecbplus", "coref_type": "CROSS_DOC_COREF", "decription": "t36_wjeffs_jul_08_charge"}, {"coref_chain": "ACT17720769677783913", "doc_id": "36_10ecbplus", "is_continuous": true, "is_singleton": false, "mention_id": "36_10ecbplus_ACT17720769677783913_3_40", "mention_type": "ACT", "mention_full_type": "ACTION_OCCURRENCE", "score": -1.0, "sent_id": 2, "tokens_number": [40], "tokens_str": "charges", "topic_id": "36ecbplus", "coref_type": "CROSS_DOC_COREF", "decription": "t36_wjeffs_jul_08_charge"}, {"coref_chain": "ACT17720769677783913", "doc_id": "36_8ecbplus", "is_continuous": true, "is_singleton": false, "mention_id": "36_8ecbplus_ACT17720769677783913_3_7", "mention_type": "ACT", "mention_full_type": "ACTION_OCCURRENCE", "score": -1.0, "sent_id": 2, "tokens_number": [7], "tokens_str": "charged", "topic_id": "36ecbplus", "coref_type": "CROSS_DOC_COREF", "decription": "t36_wjeffs_jul_08_charge"}, {"coref_chain": "ACT28673542302134352", "doc_id": "36_11ecbplus", "is_continuous": true, "is_singleton": true, "mention_id": "36_11ecbplus_ACT28673542302134352_4_10", "mention_type": "ACT", "mention_full_type": "ACTION_OCCURRENCE", "score": -1.0, "sent_id": 3, "tokens_number": [10], "tokens_str": "raping", "topic_id": "36ecbplus", "coref_type": "CROSS_DOC_COREF", "decription": "t36_rape_two counts"}, {"coref_chain": "ACT17716990655179680", "doc_id": "36_11ecbplus", "is_continuous": true, "is_singleton": false, "mention_id": "36_11ecbplus_ACT17716990655179680_12_22", "mention_type": "ACT", "mention_full_type": "ACTION_OCCURRENCE", "score": -1.0, "sent_id": 11, "tokens_number": [22], "tokens_str": "marriage", "topic_id": "36ecbplus", "coref_type": "CROSS_DOC_COREF", "decription": "t36_spiritual_marriages"}, {"coref_chain": "ACT17716990655179680", "doc_id": "36_11ecbplus", "is_continuous": true, "is_singleton": false, "mention_id": "36_11ecbplus_ACT17716990655179680_1_6", "mention_type": "ACT", "mention_full_type": "ACTION_OCCURRENCE", "score": -1.0, "sent_id": 1, "tokens_number": [6], "tokens_str": "Marriage", "topic_id": "36ecbplus", "coref_type": "CROSS_DOC_COREF", "decription": "t36_spiritual_marriages"}, {"coref_chain": "ACT17716990655179680", "doc_id": "36_2ecbplus", "is_continuous": true, "is_singleton": false, "mention_id": "36_2ecbplus_ACT17716990655179680_13_30", "mention_type": "ACT", "mention_full_type": "ACTION_OCCURRENCE", "score": -1.0, "sent_id": 12, "tokens_number": [30], "tokens_str": "marriage\"", "topic_id": "36ecbplus", "coref_type": "CROSS_DOC_COREF", "decription": "t36_spiritual_marriages"}, {"coref_chain": "ACT17716990655179680", "doc_id": "36_3ecbplus", "is_continuous": true, "is_singleton": false, "mention_id": "36_3ecbplus_ACT17716990655179680_3_31", "mention_type": "ACT", "mention_full_type": "ACTION_OCCURRENCE", "score": -1.0, "sent_id": 2, "tokens_number": [31, 32], "tokens_str": "\"spiritual marriages", "topic_id": "36ecbplus", "coref_type": "CROSS_DOC_COREF", "decription": "t36_spiritual_marriages"}, {"coref_chain": "ACT17716990655179680", "doc_id": "36_4ecbplus", "is_continuous": true, "is_singleton": false, "mention_id": "36_4ecbplus_ACT17716990655179680_16_24", "mention_type": "ACT", "mention_full_type": "ACTION_OCCURRENCE", "score": -1.0, "sent_id": 15, "tokens_number": [24], "tokens_str": "marriages", "topic_id": "36ecbplus", "coref_type": "CROSS_DOC_COREF", "decription": "t36_spiritual_marriages"}, {"coref_chain": "ACT17716990655179680", "doc_id": "36_5ecbplus", "is_continuous": true, "is_singleton": false, "mention_id": "36_5ecbplus_ACT17716990655179680_7_23", "mention_type": "ACT", "mention_full_type": "ACTION_OCCURRENCE", "score": -1.0, "sent_id": 6, "tokens_number": [23, 24], "tokens_str": "illegal marriages", "topic_id": "36ecbplus", "coref_type": "CROSS_DOC_COREF", "decription": "t36_spiritual_marriages"}, {"coref_chain": "ACT17716990655179680", "doc_id": "36_6ecbplus", "is_continuous": true, "is_singleton": false, "mention_id": "36_6ecbplus_ACT17716990655179680_3_31", "mention_type": "ACT", "mention_full_type": "ACTION_OCCURRENCE", "score": -1.0, "sent_id": 2, "tokens_number": [31, 32], "tokens_str": "\"spiritual marriages", "topic_id": "36ecbplus", "coref_type": "CROSS_DOC_COREF", "decription": "t36_spiritual_marriages"}, {"coref_chain": "ACT17716990655179680", "doc_id": "36_8ecbplus", "is_continuous": true, "is_singleton": false, "mention_id": "36_8ecbplus_ACT17716990655179680_3_14", "mention_type": "ACT", "mention_full_type": "ACTION_OCCURRENCE", "score": -1.0, "sent_id": 2, "tokens_number": [14, 15], "tokens_str": "polygamous marriages", "topic_id": "36ecbplus", "coref_type": "CROSS_DOC_COREF", "decription": "t36_spiritual_marriages"}, {"coref_chain": "ACT28671684617581995", "doc_id": "36_11ecbplus", "is_continuous": true, "is_singleton": true, "mention_id": "36_11ecbplus_ACT28671684617581995_1_8", "mention_type": "ACT", "mention_full_type": "ACTION_OCCURRENCE", "score": -1.0, "sent_id": 1, "tokens_number": [8], "tokens_str": "Polygamy", "topic_id": "36ecbplus", "coref_type": "CROSS_DOC_COREF", "decription": "t36_polygamy"}, {"coref_chain": "ACT17642344350988871", "doc_id": "36_11ecbplus", "is_continuous": true, "is_singleton": false, "mention_id": "36_11ecbplus_ACT17642344350988871_4_2", "mention_type": "ACT", "mention_full_type": "ACTION_OCCURRENCE", "score": -1.0, "sent_id": 3, "tokens_number": [2], "tokens_str": "charged", "topic_id": "36ecbplus", "coref_type": "CROSS_DOC_COREF", "decription": "t36_charged"}, {"coref_chain": "ACT17642344350988871", "doc_id": "36_1ecbplus", "is_continuous": true, "is_singleton": false, "mention_id": "36_1ecbplus_ACT17642344350988871_4_18", "mention_type": "ACT", "mention_full_type": "ACTION_OCCURRENCE", "score": -1.0, "sent_id": 3, "tokens_number": [18], "tokens_str": "charged", "topic_id": "36ecbplus", "coref_type": "CROSS_DOC_COREF", "decription": "t36_charged"}, {"coref_chain": "ACT17642344350988871", "doc_id": "36_1ecbplus", "is_continuous": true, "is_singleton": false, "mention_id": "36_1ecbplus_ACT17642344350988871_3_15", "mention_type": "ACT", "mention_full_type": "ACTION_OCCURRENCE", "score": -1.0, "sent_id": 2, "tokens_number": [15], "tokens_str": "charges", "topic_id": "36ecbplus", "coref_type": "CROSS_DOC_COREF", "decription": "t36_charged"}, {"coref_chain": "ACT17642344350988871", "doc_id": "36_1ecbplus", "is_continuous": true, "is_singleton": false, "mention_id": "36_1ecbplus_ACT17642344350988871_1_7", "mention_type": "ACT", "mention_full_type": "ACTION_OCCURRENCE", "score": -1.0, "sent_id": 1, "tokens_number": [7], "tokens_str": "Charges", "topic_id": "36ecbplus", "coref_type": "CROSS_DOC_COREF", "decription": "t36_charged"}, {"coref_chain": "ACT17642344350988871", "doc_id": "36_4ecbplus", "is_continuous": true, "is_singleton": false, "mention_id": "36_4ecbplus_ACT17642344350988871_16_2", "mention_type": "ACT", "mention_full_type": "ACTION_OCCURRENCE", "score": -1.0, "sent_id": 15, "tokens_number": [2], "tokens_str": "accused", "topic_id": "36ecbplus", "coref_type": "CROSS_DOC_COREF", "decription": "t36_charged"}, {"coref_chain": "ACT17642344350988871", "doc_id": "36_4ecbplus", "is_continuous": true, "is_singleton": false, "mention_id": "36_4ecbplus_ACT17642344350988871_3_18", "mention_type": "ACT", "mention_full_type": "ACTION_OCCURRENCE", "score": -1.0, "sent_id": 2, "tokens_number": [18], "tokens_str": "charged", "topic_id": "36ecbplus", "coref_type": "CROSS_DOC_COREF", "decription": "t36_charged"}, {"coref_chain": "ACT17642344350988871", "doc_id": "36_5ecbplus", "is_continuous": true, "is_singleton": false, "mention_id": "36_5ecbplus_ACT17642344350988871_7_1", "mention_type": "ACT", "mention_full_type": "ACTION_OCCURRENCE", "score": -1.0, "sent_id": 6, "tokens_number": [1], "tokens_str": "charged", "topic_id": "36ecbplus", "coref_type": "CROSS_DOC_COREF", "decription": "t36_charged"}, {"coref_chain": "ACT17642344350988871", "doc_id": "36_6ecbplus", "is_continuous": true, "is_singleton": false, "mention_id": "36_6ecbplus_ACT17642344350988871_1_7", "mention_type": "ACT", "mention_full_type": "ACTION_OCCURRENCE", "score": -1.0, "sent_id": 1, "tokens_number": [7], "tokens_str": "charges", "topic_id": "36ecbplus", "coref_type": "CROSS_DOC_COREF", "decription": "t36_charged"}, {"coref_chain": "ACT17642344350988871", "doc_id": "36_9ecbplus", "is_continuous": true, "is_singleton": false, "mention_id": "36_9ecbplus_ACT17642344350988871_1_7", "mention_type": "ACT", "mention_full_type": "ACTION_OCCURRENCE", "score": -1.0, "sent_id": 1, "tokens_number": [7], "tokens_str": "charges", "topic_id": "36ecbplus", "coref_type": "CROSS_DOC_COREF", "decription": "t36_charged"}, {"coref_chain": "ACT17642344350988871", "doc_id": "36_9ecbplus", "is_continuous": true, "is_singleton": false, "mention_id": "36_9ecbplus_ACT17642344350988871_6_3", "mention_type": "ACT", "mention_full_type": "ACTION_OCCURRENCE", "score": -1.0, "sent_id": 5, "tokens_number": [3], "tokens_str": "charged", "topic_id": "36ecbplus", "coref_type": "CROSS_DOC_COREF", "decription": "t36_charged"}, {"coref_chain": "ACT17642344350988871", "doc_id": "36_9ecbplus", "is_continuous": true, "is_singleton": false, "mention_id": "36_9ecbplus_ACT17642344350988871_3_26", "mention_type": "ACT", "mention_full_type": "ACTION_OCCURRENCE", "score": -1.0, "sent_id": 2, "tokens_number": [26], "tokens_str": "charges", "topic_id": "36ecbplus", "coref_type": "CROSS_DOC_COREF", "decription": "t36_charged"}, {"coref_chain": "ACT17717083178139489", "doc_id": "36_11ecbplus", "is_continuous": true, "is_singleton": false, "mention_id": "36_11ecbplus_ACT17717083178139489_4_17", "mention_type": "ACT", "mention_full_type": "ACTION_OCCURRENCE", "score": -1.0, "sent_id": 3, "tokens_number": [17], "tokens_str": "fathering", "topic_id": "36ecbplus", "coref_type": "CROSS_DOC_COREF", "decription": "t36_wjeffs_fathered_child"}, {"coref_chain": "ACT17717083178139489", "doc_id": "36_3ecbplus", "is_continuous": true, "is_singleton": false, "mention_id": "36_3ecbplus_ACT17717083178139489_8_7", "mention_type": "ACT", "mention_full_type": "ACTION_OCCURRENCE", "score": -1.0, "sent_id": 7, "tokens_number": [7], "tokens_str": "fathered", "topic_id": "36ecbplus", "coref_type": "CROSS_DOC_COREF", "decription": "t36_wjeffs_fathered_child"}, {"coref_chain": "ACT17717083178139489", "doc_id": "36_5ecbplus", "is_continuous": true, "is_singleton": false, "mention_id": "36_5ecbplus_ACT17717083178139489_8_10", "mention_type": "ACT", "mention_full_type": "ACTION_OCCURRENCE", "score": -1.0, "sent_id": 7, "tokens_number": [10], "tokens_str": "fathered", "topic_id": "36ecbplus", "coref_type": "CROSS_DOC_COREF", "decription": "t36_wjeffs_fathered_child"}, {"coref_chain": "ACT17717033296379310", "doc_id": "36_11ecbplus", "is_continuous": true, "is_singleton": false, "mention_id": "36_11ecbplus_ACT17717033296379310_1_2", "mention_type": "ACT", "mention_full_type": "ACTION_OCCURRENCE", "score": -1.0, "sent_id": 1, "tokens_number": [2], "tokens_str": "Trial", "topic_id": "36ecbplus", "coref_type": "CROSS_DOC_COREF", "decription": "t36_trial"}, {"coref_chain": "ACT17717033296379310", "doc_id": "36_11ecbplus", "is_continuous": true, "is_singleton": false, "mention_id": "36_11ecbplus_ACT17717033296379310_3_22", "mention_type": "ACT", "mention_full_type": "ACTION_OCCURRENCE", "score": -1.0, "sent_id": 2, "tokens_number": [22], "tokens_str": "trial", "topic_id": "36ecbplus", "coref_type": "CROSS_DOC_COREF", "decription": "t36_trial"}, {"coref_chain": "ACT17717033296379310", "doc_id": "36_2ecbplus", "is_continuous": true, "is_singleton": false, "mention_id": "36_2ecbplus_ACT17717033296379310_13_24", "mention_type": "ACT", "mention_full_type": "ACTION_OCCURRENCE", "score": -1.0, "sent_id": 12, "tokens_number": [24], "tokens_str": "trial", "topic_id": "36ecbplus", "coref_type": "CROSS_DOC_COREF", "decription": "t36_trial"}, {"coref_chain": "ACT17717033296379310", "doc_id": "36_4ecbplus", "is_continuous": true, "is_singleton": false, "mention_id": "36_4ecbplus_ACT17717033296379310_3_11", "mention_type": "ACT", "mention_full_type": "ACTION_OCCURRENCE", "score": -1.0, "sent_id": 2, "tokens_number": [11], "tokens_str": "trial", "topic_id": "36ecbplus", "coref_type": "CROSS_DOC_COREF", "decription": "t36_trial"}, {"coref_chain": "ACT17717033296379310", "doc_id": "36_9ecbplus", "is_continuous": true, "is_singleton": false, "mention_id": "36_9ecbplus_ACT17717033296379310_3_20", "mention_type": "ACT", "mention_full_type": "ACTION_OCCURRENCE", "score": -1.0, "sent_id": 2, "tokens_number": [20], "tokens_str": "trial", "topic_id": "36ecbplus", "coref_type": "CROSS_DOC_COREF", "decription": "t36_trial"}, {"coref_chain": "ACT17642254010313856", "doc_id": "36_11ecbplus", "is_continuous": true, "is_singleton": false, "mention_id": "36_11ecbplus_ACT17642254010313856_4_7", "mention_type": "ACT", "mention_full_type": "ACTION_OCCURRENCE", "score": -1.0, "sent_id": 3, "tokens_number": [7, 8], "tokens_str": "sexual assault", "topic_id": "36ecbplus", "coref_type": "CROSS_DOC_COREF", "decription": "t36_assault_charges"}, {"coref_chain": "ACT17642254010313856", "doc_id": "36_1ecbplus", "is_continuous": true, "is_singleton": false, "mention_id": "36_1ecbplus_ACT17642254010313856_4_20", "mention_type": "ACT", "mention_full_type": "ACTION_OCCURRENCE", "score": -1.0, "sent_id": 3, "tokens_number": [20, 21], "tokens_str": "sexual assault", "topic_id": "36ecbplus", "coref_type": "CROSS_DOC_COREF", "decription": "t36_assault_charges"}, {"coref_chain": "ACT17642254010313856", "doc_id": "36_1ecbplus", "is_continuous": true, "is_singleton": false, "mention_id": "36_1ecbplus_ACT17642254010313856_3_13", "mention_type": "ACT", "mention_full_type": "ACTION_OCCURRENCE", "score": -1.0, "sent_id": 2, "tokens_number": [13, 14], "tokens_str": "sexual assault", "topic_id": "36ecbplus", "coref_type": "CROSS_DOC_COREF", "decription": "t36_assault_charges"}, {"coref_chain": "ACT17642254010313856", "doc_id": "36_1ecbplus", "is_continuous": true, "is_singleton": false, "mention_id": "36_1ecbplus_ACT17642254010313856_1_5", "mention_type": "ACT", "mention_full_type": "ACTION_OCCURRENCE", "score": -1.0, "sent_id": 1, "tokens_number": [5, 6], "tokens_str": "Sexual Assault", "topic_id": "36ecbplus", "coref_type": "CROSS_DOC_COREF", "decription": "t36_assault_charges"}, {"coref_chain": "ACT17642254010313856", "doc_id": "36_2ecbplus", "is_continuous": true, "is_singleton": false, "mention_id": "36_2ecbplus_ACT17642254010313856_5_9", "mention_type": "ACT", "mention_full_type": "ACTION_OCCURRENCE", "score": -1.0, "sent_id": 4, "tokens_number": [9, 10, 11], "tokens_str": "aggravated sexual assault", "topic_id": "36ecbplus", "coref_type": "CROSS_DOC_COREF", "decription": "t36_assault_charges"}, {"coref_chain": "ACT17642254010313856", "doc_id": "36_2ecbplus", "is_continuous": true, "is_singleton": false, "mention_id": "36_2ecbplus_ACT17642254010313856_5_27", "mention_type": "ACT", "mention_full_type": "ACTION_OCCURRENCE", "score": -1.0, "sent_id": 4, "tokens_number": [27, 28], "tokens_str": "sexual assault", "topic_id": "36ecbplus", "coref_type": "CROSS_DOC_COREF", "decription": "t36_assault_charges"}, {"coref_chain": "ACT17642254010313856", "doc_id": "36_2ecbplus", "is_continuous": true, "is_singleton": false, "mention_id": "36_2ecbplus_ACT17642254010313856_12_3", "mention_type": "ACT", "mention_full_type": "ACTION_OCCURRENCE", "score": -1.0, "sent_id": 11, "tokens_number": [3], "tokens_str": "forcing", "topic_id": "36ecbplus", "coref_type": "CROSS_DOC_COREF", "decription": "t36_assault_charges"}, {"coref_chain": "ACT17642254010313856", "doc_id": "36_2ecbplus", "is_continuous": true, "is_singleton": false, "mention_id": "36_2ecbplus_ACT17642254010313856_12_4", "mention_type": "ACT", "mention_full_type": "ACTION_OCCURRENCE", "score": -1.0, "sent_id": 11, "tokens_number": [4], "tokens_str": "sex", "topic_id": "36ecbplus", "coref_type": "CROSS_DOC_COREF", "decription": "t36_assault_charges"}, {"coref_chain": "ACT17642254010313856", "doc_id": "36_2ecbplus", "is_continuous": true, "is_singleton": false, "mention_id": "36_2ecbplus_ACT17642254010313856_3_15", "mention_type": "ACT", "mention_full_type": "ACTION_OCCURRENCE", "score": -1.0, "sent_id": 2, "tokens_number": [15, 16], "tokens_str": "sexually assaulting", "topic_id": "36ecbplus", "coref_type": "CROSS_DOC_COREF", "decription": "t36_assault_charges"}, {"coref_chain": "ACT17642254010313856", "doc_id": "36_3ecbplus", "is_continuous": true, "is_singleton": false, "mention_id": "36_3ecbplus_ACT17642254010313856_3_11", "mention_type": "ACT", "mention_full_type": "ACTION_OCCURRENCE", "score": -1.0, "sent_id": 2, "tokens_number": [11, 12], "tokens_str": "sexual assault", "topic_id": "36ecbplus", "coref_type": "CROSS_DOC_COREF", "decription": "t36_assault_charges"}, {"coref_chain": "ACT17642254010313856", "doc_id": "36_3ecbplus", "is_continuous": true, "is_singleton": false, "mention_id": "36_3ecbplus_ACT17642254010313856_1_9", "mention_type": "ACT", "mention_full_type": "ACTION_OCCURRENCE", "score": -1.0, "sent_id": 1, "tokens_number": [9, 10], "tokens_str": "Sexual Assault", "topic_id": "36ecbplus", "coref_type": "CROSS_DOC_COREF", "decription": "t36_assault_charges"}, {"coref_chain": "ACT17642254010313856", "doc_id": "36_4ecbplus", "is_continuous": true, "is_singleton": false, "mention_id": "36_4ecbplus_ACT17642254010313856_16_4", "mention_type": "ACT", "mention_full_type": "ACTION_OCCURRENCE", "score": -1.0, "sent_id": 15, "tokens_number": [4, 5], "tokens_str": "sexually assaulting", "topic_id": "36ecbplus", "coref_type": "CROSS_DOC_COREF", "decription": "t36_assault_charges"}, {"coref_chain": "ACT17642254010313856", "doc_id": "36_4ecbplus", "is_continuous": true, "is_singleton": false, "mention_id": "36_4ecbplus_ACT17642254010313856_3_20", "mention_type": "ACT", "mention_full_type": "ACTION_OCCURRENCE", "score": -1.0, "sent_id": 2, "tokens_number": [20, 21], "tokens_str": "sexually assaulting", "topic_id": "36ecbplus", "coref_type": "CROSS_DOC_COREF", "decription": "t36_assault_charges"}, {"coref_chain": "ACT17642254010313856", "doc_id": "36_5ecbplus", "is_continuous": true, "is_singleton": false, "mention_id": "36_5ecbplus_ACT17642254010313856_2_22", "mention_type": "ACT", "mention_full_type": "ACTION_OCCURRENCE", "score": -1.0, "sent_id": 2, "tokens_number": [22, 23], "tokens_str": "sexually assaulting", "topic_id": "36ecbplus", "coref_type": "CROSS_DOC_COREF", "decription": "t36_assault_charges"}, {"coref_chain": "ACT17642254010313856", "doc_id": "36_5ecbplus", "is_continuous": true, "is_singleton": false, "mention_id": "36_5ecbplus_ACT17642254010313856_7_11", "mention_type": "ACT", "mention_full_type": "ACTION_OCCURRENCE", "score": -1.0, "sent_id": 6, "tokens_number": [11, 12], "tokens_str": "sexually assaulted", "topic_id": "36ecbplus", "coref_type": "CROSS_DOC_COREF", "decription": "t36_assault_charges"}, {"coref_chain": "ACT17642254010313856", "doc_id": "36_6ecbplus", "is_continuous": true, "is_singleton": false, "mention_id": "36_6ecbplus_ACT17642254010313856_1_5", "mention_type": "ACT", "mention_full_type": "ACTION_OCCURRENCE", "score": -1.0, "sent_id": 1, "tokens_number": [5, 6], "tokens_str": "sexual assault", "topic_id": "36ecbplus", "coref_type": "CROSS_DOC_COREF", "decription": "t36_assault_charges"}, {"coref_chain": "ACT17642254010313856", "doc_id": "36_6ecbplus", "is_continuous": true, "is_singleton": false, "mention_id": "36_6ecbplus_ACT17642254010313856_3_11", "mention_type": "ACT", "mention_full_type": "ACTION_OCCURRENCE", "score": -1.0, "sent_id": 2, "tokens_number": [11, 12], "tokens_str": "sexual assault", "topic_id": "36ecbplus", "coref_type": "CROSS_DOC_COREF", "decription": "t36_assault_charges"}, {"coref_chain": "ACT17642254010313856", "doc_id": "36_8ecbplus", "is_continuous": true, "is_singleton": false, "mention_id": "36_8ecbplus_ACT17642254010313856_3_9", "mention_type": "ACT", "mention_full_type": "ACTION_OCCURRENCE", "score": -1.0, "sent_id": 2, "tokens_number": [9, 10], "tokens_str": "sex crimes", "topic_id": "36ecbplus", "coref_type": "CROSS_DOC_COREF", "decription": "t36_assault_charges"}, {"coref_chain": "ACT17642254010313856", "doc_id": "36_9ecbplus", "is_continuous": true, "is_singleton": false, "mention_id": "36_9ecbplus_ACT17642254010313856_3_24", "mention_type": "ACT", "mention_full_type": "ACTION_OCCURRENCE", "score": -1.0, "sent_id": 2, "tokens_number": [24, 25], "tokens_str": "sexual assault", "topic_id": "36ecbplus", "coref_type": "CROSS_DOC_COREF", "decription": "t36_assault_charges"}, {"coref_chain": "ACT17642254010313856", "doc_id": "36_9ecbplus", "is_continuous": true, "is_singleton": false, "mention_id": "36_9ecbplus_ACT17642254010313856_1_6", "mention_type": "ACT", "mention_full_type": "ACTION_OCCURRENCE", "score": -1.0, "sent_id": 1, "tokens_number": [6], "tokens_str": "sex", "topic_id": "36ecbplus", "coref_type": "CROSS_DOC_COREF", "decription": "t36_assault_charges"}, {"coref_chain": "ACT17642254010313856", "doc_id": "36_9ecbplus", "is_continuous": true, "is_singleton": false, "mention_id": "36_9ecbplus_ACT17642254010313856_6_22", "mention_type": "ACT", "mention_full_type": "ACTION_OCCURRENCE", "score": -1.0, "sent_id": 5, "tokens_number": [22, 23, 24], "tokens_str": "aggravated sexual assault", "topic_id": "36ecbplus", "coref_type": "CROSS_DOC_COREF", "decription": "t36_assault_charges"}, {"coref_chain": "ACT17642310630333551", "doc_id": "36_1ecbplus", "is_continuous": true, "is_singleton": false, "mention_id": "36_1ecbplus_ACT17642310630333551_8_12", "mention_type": "ACT", "mention_full_type": "ACTION_OCCURRENCE", "score": -1.0, "sent_id": 7, "tokens_number": [12], "tokens_str": "played", "topic_id": "36ecbplus", "coref_type": "CROSS_DOC_COREF", "decription": "t36_played_audio"}, {"coref_chain": "ACT17642310630333551", "doc_id": "36_2ecbplus", "is_continuous": true, "is_singleton": false, "mention_id": "36_2ecbplus_ACT17642310630333551_13_19", "mention_type": "ACT", "mention_full_type": "ACTION_OCCURRENCE", "score": -1.0, "sent_id": 12, "tokens_number": [19], "tokens_str": "played", "topic_id": "36ecbplus", "coref_type": "CROSS_DOC_COREF", "decription": "t36_played_audio"}, {"coref_chain": "ACT17642310630333551", "doc_id": "36_3ecbplus", "is_continuous": true, "is_singleton": false, "mention_id": "36_3ecbplus_ACT17642310630333551_8_19", "mention_type": "ACT", "mention_full_type": "ACTION_OCCURRENCE", "score": -1.0, "sent_id": 7, "tokens_number": [19], "tokens_str": "played", "topic_id": "36ecbplus", "coref_type": "CROSS_DOC_COREF", "decription": "t36_played_audio"}, {"coref_chain": "ACT17642310630333551", "doc_id": "36_4ecbplus", "is_continuous": true, "is_singleton": false, "mention_id": "36_4ecbplus_ACT17642310630333551_3_2", "mention_type": "ACT", "mention_full_type": "ACTION_OCCURRENCE", "score": -1.0, "sent_id": 2, "tokens_number": [2, 3], "tokens_str": "put on", "topic_id": "36ecbplus", "coref_type": "CROSS_DOC_COREF", "decription": "t36_played_audio"}, {"coref_chain": "ACT17642310630333551", "doc_id": "36_4ecbplus", "is_continuous": true, "is_singleton": false, "mention_id": "36_4ecbplus_ACT17642310630333551_4_1", "mention_type": "ACT", "mention_full_type": "ACTION_OCCURRENCE", "score": -1.0, "sent_id": 3, "tokens_number": [1], "tokens_str": "played", "topic_id": "36ecbplus", "coref_type": "CROSS_DOC_COREF", "decription": "t36_played_audio"}, {"coref_chain": "ACT17642310630333551", "doc_id": "36_5ecbplus", "is_continuous": true, "is_singleton": false, "mention_id": "36_5ecbplus_ACT17642310630333551_9_2", "mention_type": "ACT", "mention_full_type": "ACTION_OCCURRENCE", "score": -1.0, "sent_id": 8, "tokens_number": [2], "tokens_str": "played", "topic_id": "36ecbplus", "coref_type": "CROSS_DOC_COREF", "decription": "t36_played_audio"}, {"coref_chain": "ACT17642273140507825", "doc_id": "36_1ecbplus", "is_continuous": true, "is_singleton": false, "mention_id": "36_1ecbplus_ACT17642273140507825_8_22", "mention_type": "ACT", "mention_full_type": "ACTION_OCCURRENCE", "score": -1.0, "sent_id": 7, "tokens_number": [22, 23], "tokens_str": "sexually assaulting", "topic_id": "36ecbplus", "coref_type": "CROSS_DOC_COREF", "decription": "t36_assaulting_girl"}, {"coref_chain": "ACT17642273140507825", "doc_id": "36_3ecbplus", "is_continuous": true, "is_singleton": false, "mention_id": "36_3ecbplus_ACT17642273140507825_8_29", "mention_type": "ACT", "mention_full_type": "ACTION_OCCURRENCE", "score": -1.0, "sent_id": 7, "tokens_number": [29, 30], "tokens_str": "sexually assaulting", "topic_id": "36ecbplus", "coref_type": "CROSS_DOC_COREF", "decription": "t36_assaulting_girl"}, {"coref_chain": "ACT17642273140507825", "doc_id": "36_5ecbplus", "is_continuous": true, "is_singleton": false, "mention_id": "36_5ecbplus_ACT17642273140507825_9_9", "mention_type": "ACT", "mention_full_type": "ACTION_OCCURRENCE", "score": -1.0, "sent_id": 8, "tokens_number": [9, 10, 11, 12], "tokens_str": "engaging in sexual intercourse", "topic_id": "36ecbplus", "coref_type": "CROSS_DOC_COREF", "decription": "t36_assaulting_girl"}, {"coref_chain": "ACT17642293426842922", "doc_id": "36_1ecbplus", "is_continuous": true, "is_singleton": false, "mention_id": "36_1ecbplus_ACT17642293426842922_1_3", "mention_type": "ACT", "mention_full_type": "ACTION_STATE", "score": -1.0, "sent_id": 1, "tokens_number": [3], "tokens_str": "Guilty", "topic_id": "36ecbplus", "coref_type": "CROSS_DOC_COREF", "decription": "t36_guilty"}, {"coref_chain": "ACT17642293426842922", "doc_id": "36_1ecbplus", "is_continuous": true, "is_singleton": false, "mention_id": "36_1ecbplus_ACT17642293426842922_3_10", "mention_type": "ACT", "mention_full_type": "ACTION_STATE", "score": -1.0, "sent_id": 2, "tokens_number": [10], "tokens_str": "guilty", "topic_id": "36ecbplus", "coref_type": "CROSS_DOC_COREF", "decription": "t36_guilty"}, {"coref_chain": "ACT17712005011103537", "doc_id": "36_1ecbplus", "is_continuous": true, "is_singleton": false, "mention_id": "36_1ecbplus_ACT17712005011103537_8_19", "mention_type": "ACT", "mention_full_type": "ACTION_REPORTING", "score": -1.0, "sent_id": 7, "tokens_number": [19], "tokens_str": "alleged", "topic_id": "36ecbplus", "coref_type": "CROSS_DOC_COREF", "decription": "t36_prosection_said_audio"}, {"coref_chain": "ACT17712005011103537", "doc_id": "36_2ecbplus", "is_continuous": true, "is_singleton": false, "mention_id": "36_2ecbplus_ACT17712005011103537_13_37", "mention_type": "ACT", "mention_full_type": "ACTION_REPORTING", "score": -1.0, "sent_id": 12, "tokens_number": [37, 38], "tokens_str": "according to", "topic_id": "36ecbplus", "coref_type": "CROSS_DOC_COREF", "decription": "t36_prosection_said_audio"}, {"coref_chain": "ACT17712005011103537", "doc_id": "36_3ecbplus", "is_continuous": true, "is_singleton": false, "mention_id": "36_3ecbplus_ACT17712005011103537_8_26", "mention_type": "ACT", "mention_full_type": "ACTION_REPORTING", "score": -1.0, "sent_id": 7, "tokens_number": [26], "tokens_str": "said", "topic_id": "36ecbplus", "coref_type": "CROSS_DOC_COREF", "decription": "t36_prosection_said_audio"}, {"coref_chain": "ACT17642240843264095", "doc_id": "36_1ecbplus", "is_continuous": true, "is_singleton": false, "mention_id": "36_1ecbplus_ACT17642240843264095_3_5", "mention_type": "ACT", "mention_full_type": "ACTION_OCCURRENCE", "score": -1.0, "sent_id": 2, "tokens_number": [5], "tokens_str": "found", "topic_id": "36ecbplus", "coref_type": "CROSS_DOC_COREF", "decription": "t36_found_guilty"}, {"coref_chain": "ACT17642240843264095", "doc_id": "36_1ecbplus", "is_continuous": true, "is_singleton": false, "mention_id": "36_1ecbplus_ACT17642240843264095_1_2", "mention_type": "ACT", "mention_full_type": "ACTION_OCCURRENCE", "score": -1.0, "sent_id": 1, "tokens_number": [2], "tokens_str": "Found", "topic_id": "36ecbplus", "coref_type": "CROSS_DOC_COREF", "decription": "t36_found_guilty"}, {"coref_chain": "ACT17642240843264095", "doc_id": "36_1ecbplus", "is_continuous": true, "is_singleton": false, "mention_id": "36_1ecbplus_ACT17642240843264095_8_4", "mention_type": "ACT", "mention_full_type": "ACTION_OCCURRENCE", "score": -1.0, "sent_id": 7, "tokens_number": [4], "tokens_str": "decision", "topic_id": "36ecbplus", "coref_type": "CROSS_DOC_COREF", "decription": "t36_found_guilty"}, {"coref_chain": "ACT17642240843264095", "doc_id": "36_5ecbplus", "is_continuous": true, "is_singleton": false, "mention_id": "36_5ecbplus_ACT17642240843264095_2_20", "mention_type": "ACT", "mention_full_type": "ACTION_OCCURRENCE", "score": -1.0, "sent_id": 2, "tokens_number": [20], "tokens_str": "convicted", "topic_id": "36ecbplus", "coref_type": "CROSS_DOC_COREF", "decription": "t36_found_guilty"}, {"coref_chain": "ACT17712202477008858", "doc_id": "36_1ecbplus", "is_continuous": true, "is_singleton": false, "mention_id": "36_1ecbplus_ACT17712202477008858_4_26", "mention_type": "ACT", "mention_full_type": "ACTION_OCCURRENCE", "score": -1.0, "sent_id": 3, "tokens_number": [26], "tokens_str": "taking", "topic_id": "36ecbplus", "coref_type": "CROSS_DOC_COREF", "decription": "t36_warren_jeffs_took_wives"}, {"coref_chain": "ACT17712202477008858", "doc_id": "36_2ecbplus", "is_continuous": true, "is_singleton": false, "mention_id": "36_2ecbplus_ACT17712202477008858_12_17", "mention_type": "ACT", "mention_full_type": "ACTION_OCCURRENCE", "score": -1.0, "sent_id": 11, "tokens_number": [17], "tokens_str": "taken", "topic_id": "36ecbplus", "coref_type": "CROSS_DOC_COREF", "decription": "t36_warren_jeffs_took_wives"}, {"coref_chain": "ACT17712202477008858", "doc_id": "36_3ecbplus", "is_continuous": true, "is_singleton": false, "mention_id": "36_3ecbplus_ACT17712202477008858_3_23", "mention_type": "ACT", "mention_full_type": "ACTION_OCCURRENCE", "score": -1.0, "sent_id": 2, "tokens_number": [23], "tokens_str": "took", "topic_id": "36ecbplus", "coref_type": "CROSS_DOC_COREF", "decription": "t36_warren_jeffs_took_wives"}, {"coref_chain": "ACT17712202477008858", "doc_id": "36_4ecbplus", "is_continuous": true, "is_singleton": false, "mention_id": "36_4ecbplus_ACT17712202477008858_16_15", "mention_type": "ACT", "mention_full_type": "ACTION_OCCURRENCE", "score": -1.0, "sent_id": 15, "tokens_number": [15], "tokens_str": "took", "topic_id": "36ecbplus", "coref_type": "CROSS_DOC_COREF", "decription": "t36_warren_jeffs_took_wives"}, {"coref_chain": "ACT17712202477008858", "doc_id": "36_5ecbplus", "is_continuous": true, "is_singleton": false, "mention_id": "36_5ecbplus_ACT17712202477008858_2_34", "mention_type": "ACT", "mention_full_type": "ACTION_OCCURRENCE", "score": -1.0, "sent_id": 2, "tokens_number": [34], "tokens_str": "claimed", "topic_id": "36ecbplus", "coref_type": "CROSS_DOC_COREF", "decription": "t36_warren_jeffs_took_wives"}, {"coref_chain": "ACT17712202477008858", "doc_id": "36_5ecbplus", "is_continuous": true, "is_singleton": false, "mention_id": "36_5ecbplus_ACT17712202477008858_7_22", "mention_type": "ACT", "mention_full_type": "ACTION_OCCURRENCE", "score": -1.0, "sent_id": 6, "tokens_number": [22], "tokens_str": "arranging", "topic_id": "36ecbplus", "coref_type": "CROSS_DOC_COREF", "decription": "t36_warren_jeffs_took_wives"}, {"coref_chain": "ACT17712202477008858", "doc_id": "36_6ecbplus", "is_continuous": true, "is_singleton": false, "mention_id": "36_6ecbplus_ACT17712202477008858_3_23", "mention_type": "ACT", "mention_full_type": "ACTION_OCCURRENCE", "score": -1.0, "sent_id": 2, "tokens_number": [23], "tokens_str": "took", "topic_id": "36ecbplus", "coref_type": "CROSS_DOC_COREF", "decription": "t36_warren_jeffs_took_wives"}, {"coref_chain": "ACT17720027886831111", "doc_id": "36_2ecbplus", "is_continuous": true, "is_singleton": true, "mention_id": "36_2ecbplus_ACT17720027886831111_3_20", "mention_type": "ACT", "mention_full_type": "ACTION_REPORTING", "score": -1.0, "sent_id": 2, "tokens_number": [20], "tokens_str": "claimed", "topic_id": "36ecbplus", "coref_type": "CROSS_DOC_COREF", "decription": "t36_wjeffs_claims_marriage"}, {"coref_chain": "ACT17717179034710928", "doc_id": "36_2ecbplus", "is_continuous": true, "is_singleton": false, "mention_id": "36_2ecbplus_ACT17717179034710928_13_31", "mention_type": "ACT", "mention_full_type": "ACTION_OCCURRENCE", "score": -1.0, "sent_id": 12, "tokens_number": [31], "tokens_str": "instructions", "topic_id": "36ecbplus", "coref_type": "CROSS_DOC_COREF", "decription": "t36_instructing_wives"}, {"coref_chain": "ACT17717179034710928", "doc_id": "36_4ecbplus", "is_continuous": true, "is_singleton": false, "mention_id": "36_4ecbplus_ACT17717179034710928_4_7", "mention_type": "ACT", "mention_full_type": "ACTION_OCCURRENCE", "score": -1.0, "sent_id": 3, "tokens_number": [7], "tokens_str": "instructing", "topic_id": "36ecbplus", "coref_type": "CROSS_DOC_COREF", "decription": "t36_instructing_wives"}, {"coref_chain": "ACT28674637423707425", "doc_id": "36_2ecbplus", "is_continuous": true, "is_singleton": false, "mention_id": "36_2ecbplus_ACT28674637423707425_3_12", "mention_type": "ACT", "mention_full_type": "ACTION_STATE", "score": -1.0, "sent_id": 2, "tokens_number": [12, 13], "tokens_str": "20 years", "topic_id": "36ecbplus", "coref_type": "CROSS_DOC_COREF", "decription": "t36_20years_sent"}, {"coref_chain": "ACT28674637423707425", "doc_id": "36_2ecbplus", "is_continuous": true, "is_singleton": false, "mention_id": "36_2ecbplus_ACT28674637423707425_5_21", "mention_type": "ACT", "mention_full_type": "ACTION_STATE", "score": -1.0, "sent_id": 4, "tokens_number": [21, 22, 23, 24], "tokens_str": "20 years in prison", "topic_id": "36ecbplus", "coref_type": "CROSS_DOC_COREF", "decription": "t36_20years_sent"}, {"coref_chain": "ACT17720074783104766", "doc_id": "36_2ecbplus", "is_continuous": true, "is_singleton": false, "mention_id": "36_2ecbplus_ACT17720074783104766_5_2", "mention_type": "ACT", "mention_full_type": "ACTION_OCCURRENCE", "score": -1.0, "sent_id": 4, "tokens_number": [2], "tokens_str": "sentenced", "topic_id": "36ecbplus", "coref_type": "CROSS_DOC_COREF", "decription": "t36_wjeffs_sentenced_11"}, {"coref_chain": "ACT17720074783104766", "doc_id": "36_2ecbplus", "is_continuous": true, "is_singleton": false, "mention_id": "36_2ecbplus_ACT17720074783104766_3_5", "mention_type": "ACT", "mention_full_type": "ACTION_OCCURRENCE", "score": -1.0, "sent_id": 2, "tokens_number": [5], "tokens_str": "sentenced", "topic_id": "36ecbplus", "coref_type": "CROSS_DOC_COREF", "decription": "t36_wjeffs_sentenced_11"}, {"coref_chain": "ACT17720074783104766", "doc_id": "36_2ecbplus", "is_continuous": true, "is_singleton": false, "mention_id": "36_2ecbplus_ACT17720074783104766_1_4", "mention_type": "ACT", "mention_full_type": "ACTION_OCCURRENCE", "score": -1.0, "sent_id": 1, "tokens_number": [4], "tokens_str": "sentenced", "topic_id": "36ecbplus", "coref_type": "CROSS_DOC_COREF", "decription": "t36_wjeffs_sentenced_11"}, {"coref_chain": "ACT17720074783104766", "doc_id": "36_3ecbplus", "is_continuous": true, "is_singleton": false, "mention_id": "36_3ecbplus_ACT17720074783104766_1_6", "mention_type": "ACT", "mention_full_type": "ACTION_OCCURRENCE", "score": -1.0, "sent_id": 1, "tokens_number": [6], "tokens_str": "Convicted", "topic_id": "36ecbplus", "coref_type": "CROSS_DOC_COREF", "decription": "t36_wjeffs_sentenced_11"}, {"coref_chain": "ACT17720074783104766", "doc_id": "36_3ecbplus", "is_continuous": true, "is_singleton": false, "mention_id": "36_3ecbplus_ACT17720074783104766_3_3", "mention_type": "ACT", "mention_full_type": "ACTION_OCCURRENCE", "score": -1.0, "sent_id": 2, "tokens_number": [3], "tokens_str": "convicted", "topic_id": "36ecbplus", "coref_type": "CROSS_DOC_COREF", "decription": "t36_wjeffs_sentenced_11"}, {"coref_chain": "ACT17720074783104766", "doc_id": "36_5ecbplus", "is_continuous": true, "is_singleton": false, "mention_id": "36_5ecbplus_ACT17720074783104766_2_12", "mention_type": "ACT", "mention_full_type": "ACTION_OCCURRENCE", "score": -1.0, "sent_id": 2, "tokens_number": [12], "tokens_str": "sentenced", "topic_id": "36ecbplus", "coref_type": "CROSS_DOC_COREF", "decription": "t36_wjeffs_sentenced_11"}, {"coref_chain": "ACT17720074783104766", "doc_id": "36_5ecbplus", "is_continuous": true, "is_singleton": false, "mention_id": "36_5ecbplus_ACT17720074783104766_1_7", "mention_type": "ACT", "mention_full_type": "ACTION_OCCURRENCE", "score": -1.0, "sent_id": 1, "tokens_number": [7], "tokens_str": "sentenced", "topic_id": "36ecbplus", "coref_type": "CROSS_DOC_COREF", "decription": "t36_wjeffs_sentenced_11"}, {"coref_chain": "ACT17720074783104766", "doc_id": "36_6ecbplus", "is_continuous": true, "is_singleton": false, "mention_id": "36_6ecbplus_ACT17720074783104766_1_2", "mention_type": "ACT", "mention_full_type": "ACTION_OCCURRENCE", "score": -1.0, "sent_id": 1, "tokens_number": [2], "tokens_str": "convicted", "topic_id": "36ecbplus", "coref_type": "CROSS_DOC_COREF", "decription": "t36_wjeffs_sentenced_11"}, {"coref_chain": "ACT17720074783104766", "doc_id": "36_6ecbplus", "is_continuous": true, "is_singleton": false, "mention_id": "36_6ecbplus_ACT17720074783104766_3_3", "mention_type": "ACT", "mention_full_type": "ACTION_OCCURRENCE", "score": -1.0, "sent_id": 2, "tokens_number": [3], "tokens_str": "convicted", "topic_id": "36ecbplus", "coref_type": "CROSS_DOC_COREF", "decription": "t36_wjeffs_sentenced_11"}, {"coref_chain": "ACT28674653653685646", "doc_id": "36_2ecbplus", "is_continuous": true, "is_singleton": false, "mention_id": "36_2ecbplus_ACT28674653653685646_3_8", "mention_type": "ACT", "mention_full_type": "ACTION_STATE", "score": -1.0, "sent_id": 2, "tokens_number": [8, 9, 10], "tokens_str": "life in prison", "topic_id": "36ecbplus", "coref_type": "CROSS_DOC_COREF", "decription": "t36_life_in_prison_sent"}, {"coref_chain": "ACT28674653653685646", "doc_id": "36_2ecbplus", "is_continuous": true, "is_singleton": false, "mention_id": "36_2ecbplus_ACT28674653653685646_5_5", "mention_type": "ACT", "mention_full_type": "ACTION_STATE", "score": -1.0, "sent_id": 4, "tokens_number": [5, 6, 7], "tokens_str": "life in prison", "topic_id": "36ecbplus", "coref_type": "CROSS_DOC_COREF", "decription": "t36_life_in_prison_sent"}, {"coref_chain": "ACT28674653653685646", "doc_id": "36_2ecbplus", "is_continuous": true, "is_singleton": false, "mention_id": "36_2ecbplus_ACT28674653653685646_6_9", "mention_type": "ACT", "mention_full_type": "ACTION_STATE", "score": -1.0, "sent_id": 5, "tokens_number": [9, 10], "tokens_str": "life sentence", "topic_id": "36ecbplus", "coref_type": "CROSS_DOC_COREF", "decription": "t36_life_in_prison_sent"}, {"coref_chain": "ACT28674653653685646", "doc_id": "36_2ecbplus", "is_continuous": true, "is_singleton": false, "mention_id": "36_2ecbplus_ACT28674653653685646_1_6", "mention_type": "ACT", "mention_full_type": "ACTION_STATE", "score": -1.0, "sent_id": 1, "tokens_number": [6, 7, 8], "tokens_str": "life in prison", "topic_id": "36ecbplus", "coref_type": "CROSS_DOC_COREF", "decription": "t36_life_in_prison_sent"}, {"coref_chain": "ACT28674653653685646", "doc_id": "36_5ecbplus", "is_continuous": true, "is_singleton": false, "mention_id": "36_5ecbplus_ACT28674653653685646_2_14", "mention_type": "ACT", "mention_full_type": "ACTION_STATE", "score": -1.0, "sent_id": 2, "tokens_number": [14, 15, 16], "tokens_str": "life in prison", "topic_id": "36ecbplus", "coref_type": "CROSS_DOC_COREF", "decription": "t36_life_in_prison_sent"}, {"coref_chain": "ACT17716981427916248", "doc_id": "36_3ecbplus", "is_continuous": true, "is_singleton": false, "mention_id": "36_3ecbplus_ACT17716981427916248_3_30", "mention_type": "ACT", "mention_full_type": "ACTION_OCCURRENCE", "score": -1.0, "sent_id": 2, "tokens_number": [30], "tokens_str": "calls", "topic_id": "36ecbplus", "coref_type": "CROSS_DOC_COREF", "decription": "t36_church_calls_marriages"}, {"coref_chain": "ACT17716981427916248", "doc_id": "36_4ecbplus", "is_continuous": true, "is_singleton": false, "mention_id": "36_4ecbplus_ACT17716981427916248_16_22", "mention_type": "ACT", "mention_full_type": "ACTION_OCCURRENCE", "score": -1.0, "sent_id": 15, "tokens_number": [22], "tokens_str": "calls", "topic_id": "36ecbplus", "coref_type": "CROSS_DOC_COREF", "decription": "t36_church_calls_marriages"}, {"coref_chain": "ACT17716981427916248", "doc_id": "36_6ecbplus", "is_continuous": true, "is_singleton": false, "mention_id": "36_6ecbplus_ACT17716981427916248_3_30", "mention_type": "ACT", "mention_full_type": "ACTION_OCCURRENCE", "score": -1.0, "sent_id": 2, "tokens_number": [30], "tokens_str": "calls", "topic_id": "36ecbplus", "coref_type": "CROSS_DOC_COREF", "decription": "t36_church_calls_marriages"}, {"coref_chain": "ACT17717023983626610", "doc_id": "36_3ecbplus", "is_continuous": true, "is_singleton": true, "mention_id": "36_3ecbplus_ACT17717023983626610_8_1", "mention_type": "ACT", "mention_full_type": "ACTION_OCCURRENCE", "score": -1.0, "sent_id": 7, "tokens_number": [1], "tokens_str": "used", "topic_id": "36ecbplus", "coref_type": "CROSS_DOC_COREF", "decription": "t36_gave_dna_evidence"}, {"coref_chain": "ACT17717189724819004", "doc_id": "36_4ecbplus", "is_continuous": false, "is_singleton": true, "mention_id": "36_4ecbplus_ACT17717189724819004_4_24", "mention_type": "ACT", "mention_full_type": "ACTION_OCCURRENCE", "score": -1.0, "sent_id": 3, "tokens_number": [24, 26], "tokens_str": "please sexually", "topic_id": "36ecbplus", "coref_type": "CROSS_DOC_COREF", "decription": "t36_please_him"}, {"coref_chain": "ACT17712184923948809", "doc_id": "36_4ecbplus", "is_continuous": true, "is_singleton": true, "mention_id": "36_4ecbplus_ACT17712184923948809_1_2", "mention_type": "ACT", "mention_full_type": "ACTION_PERCEPTION", "score": -1.0, "sent_id": 1, "tokens_number": [2], "tokens_str": "hears", "topic_id": "36ecbplus", "coref_type": "CROSS_DOC_COREF", "decription": "t36_heard_audio"}, {"coref_chain": "ACT17720095033296675", "doc_id": "36_8ecbplus", "is_continuous": true, "is_singleton": true, "mention_id": "36_8ecbplus_ACT17720095033296675_3_17", "mention_type": "ACT", "mention_full_type": "ACTION_OCCURRENCE", "score": -1.0, "sent_id": 2, "tokens_number": [17], "tokens_str": "arranged", "topic_id": "36ecbplus", "coref_type": "CROSS_DOC_COREF", "decription": "t36_wjeffs_arrange_marriages"}, {"coref_chain": "ACT17642553422075745", "doc_id": "36_9ecbplus", "is_continuous": true, "is_singleton": false, "mention_id": "36_9ecbplus_ACT17642553422075745_6_20", "mention_type": "ACT", "mention_full_type": "ACTION_OCCURRENCE", "score": -1.0, "sent_id": 5, "tokens_number": [20], "tokens_str": "bigamy", "topic_id": "36ecbplus", "coref_type": "CROSS_DOC_COREF", "decription": "t36_bigamy_charge"}, {"coref_chain": "ACT17642553422075745", "doc_id": "36_9ecbplus", "is_continuous": true, "is_singleton": false, "mention_id": "36_9ecbplus_ACT17642553422075745_3_22", "mention_type": "ACT", "mention_full_type": "ACTION_OCCURRENCE", "score": -1.0, "sent_id": 2, "tokens_number": [22], "tokens_str": "bigamy", "topic_id": "36ecbplus", "coref_type": "CROSS_DOC_COREF", "decription": "t36_bigamy_charge"}]